{
  "users": [
    {
      "id": 1714586038330,
      "name": "سینا",
      "lastName": "وهبی ذاتی",
      "phone": 9128999480,
      "password": "Vahabi2024",
      "cartItems": []
    },
    {
      "id": 1714586562458,
      "name": "عرفان",
      "lastName": "جودت",
      "phone": 9384453312,
      "password": "Eri1403Jodat",
      "cartItems": []
    },
    {
      "id": 1714928185662,
      "name": "سید حسین",
      "lastName": "سید مجیدی",
      "phone": 9366700670,
      "password": "MrJJ1379",
      "cartItems": [
        {
          "id": 1,
          "totalPrice": 416000,
          "purchaseDate": "1403/02/17",
          "items": [
            {
              "id": 1,
              "title": "پدر پولدار پدر بی‌پول",
              "author": "رابرت کیوساکی",
              "genre": "مالی",
              "publishedDate": "2019",
              "pages": 176,
              "price": "119,000",
              "image": "images/rich-dad-poor-dad-img.jpg",
              "quantity": 1
            },
            {
              "id": 2,
              "title": "بیندیشید و ثروت‌مند شوید",
              "author": "ناپلئون هیل",
              "genre": "مالی",
              "publishedDate": "2016",
              "pages": 225,
              "price": "123,000",
              "image": "images/think-and-grow-rich.jpg",
              "quantity": 1
            },
            {
              "id": 4,
              "title": "انسان در جستجو معنا",
              "author": "ویکتور فرانکل",
              "genre": "روانشناسی",
              "publishedDate": "2020",
              "pages": 190,
              "price": "87,000",
              "image": "images/human-in-search-for-meaning.jpg",
              "quantity": 2
            }
          ]
        },
        {
          "id": 2,
          "totalPrice": 756000,
          "purchaseDate": "1403/02/17",
          "items": [
            {
              "id": 3,
              "title": "عادت‌های اتمی",
              "author": "جیمز کلیر",
              "genre": "خودسازی",
              "publishedDate": "2021",
              "pages": 186,
              "price": "98,000",
              "image": "images/atomic-habits.jpg",
              "quantity": 2
            },
            {
              "id": 5,
              "title": "تاریخ فلسفه",
              "author": "ویل دورانت",
              "genre": "فلسفه",
              "publishedDate": "2011",
              "pages": 250,
              "price": "140,000",
              "image": "images/philosophy-history.jpg",
              "quantity": 4
            }
          ]
        },
        {
          "id": 3,
          "totalPrice": 89000,
          "purchaseDate": "1403/02/17",
          "items": [
            {
              "id": 7,
              "title": "اثر مرکب",
              "author": "دارن هاردی",
              "genre": "خودسازی",
              "publishedDate": "2005",
              "pages": 178,
              "price": "89,000",
              "image": "images/compound-effect.jpg",
              "quantity": 1
            }
          ]
        }
      ]
    },
    {
      "id": 1715452748921,
      "name": "اسم تست جدید",
      "lastName": "فامیلی شخص جدید",
      "phone": 9185645789,
      "password": "YeRamze4test",
      "cartItems": []
    },
    {
      "id": 1715615043258,
      "name": "آاا",
      "lastName": "آاا",
      "phone": 9125566773,
      "password": "Pass2023",
      "cartItems": []
    }
  ]
}